nameko_log_context.py
setup.cfg
setup.py
nameko_log_context.egg-info/PKG-INFO
nameko_log_context.egg-info/SOURCES.txt
nameko_log_context.egg-info/dependency_links.txt
nameko_log_context.egg-info/requires.txt
nameko_log_context.egg-info/top_level.txt