Metadata-Version: 1.0
Name: nameko-log-context
Version: 0.0.2
Summary: worker_ctx custom fields logging
Home-page: https://github.com/fraglab/nameko-log-context
Author: Maxim Kiyan
Author-email: maxim.k@fraglab.com
License: UNKNOWN
Platform: UNKNOWN
